setup.py
km_sdk/__init__.py
km_sdk/api_provider.py
km_sdk/cons.py
km_sdk.egg-info/PKG-INFO
km_sdk.egg-info/SOURCES.txt
km_sdk.egg-info/dependency_links.txt
km_sdk.egg-info/requires.txt
km_sdk.egg-info/top_level.txt
km_sdk/test_utils/__init__.py
km_sdk/test_utils/cache_setting_test.py
km_sdk/utils/__init__.py
km_sdk/utils/cache_utils.py
km_sdk/utils/files_utils.py
km_sdk/utils/lock_utils.py
km_sdk/utils/log_utils.py
km_sdk/utils/notification_utils.py
km_sdk/utils/scheduler_utils.py
km_sdk/utils/setting_utils.py
km_sdk/utils/webhook_utils.py